.gitignore
LICENSE.txt
README.md
requirements.txt
setup.cfg
setup.py
.github/workflows/build-and-test.yml
.github/workflows/push-to-pip.yml
glassbox_sdk/glassbox.py
glassbox_sdk/glassbox_config.py
glassbox_sdk/glassbox_inference.py
glassbox_sdk/glassbox_model.py
glassbox_sdk/factory/json_model_factory.py
glassbox_sdk/factory/xy_model_factory.py
glassbox_sdk/mixin/data_mixin.py
glassbox_sdk/mixin/http_mixin.py
glassbox_sdk/spi/__init__.py
glassbox_sdk/spi/action.py
glassbox_sdk/spi/back.py
glassbox_sdk/spi/benchmark.py
glassbox_sdk/spi/code.py
glassbox_sdk/spi/data.py
glassbox_sdk/spi/label.py
glassbox_sdk/spi/license.py
glassbox_sdk/spi/property.py
glassbox_sdk/spi/traceable.py
glassbox_sdk/spi/validation.py
tests/abc_test.py
tests/glassbox_inference_test.py
tests/glassbox_model_test.py
tests/testrunner/glassbox_testrunner_test.py
tests/testrunner/main.py
x_and_y.glassbox_sdk.egg-info/PKG-INFO
x_and_y.glassbox_sdk.egg-info/SOURCES.txt
x_and_y.glassbox_sdk.egg-info/dependency_links.txt
x_and_y.glassbox_sdk.egg-info/requires.txt
x_and_y.glassbox_sdk.egg-info/top_level.txt