Metadata-Version: 2.1
Name: x-and-y.glassbox-sdk
Version: 0.1.0
Summary: The sdk for the glassbox service
Home-page: https://github.com/c7nw3r/glassbox-sdk-python
Author: x-and-y
Author-email: christian.weber@leftshift.one
License: Apache Software License
Download-URL: https://github.com/c7nw3r/glassbox-sdk-python/archive/refs/tags/v0.1.0.tar.gz
Keywords: machine-learning,artificial-intelligence,explainable-ai
Platform: UNKNOWN
Classifier: Development Status :: 4 - Beta
Classifier: Intended Audience :: Developers
Classifier: Topic :: Scientific/Engineering :: Artificial Intelligence
Classifier: License :: OSI Approved :: Apache Software License
Classifier: Programming Language :: Python :: 3
Classifier: Programming Language :: Python :: 3.4
Classifier: Programming Language :: Python :: 3.5
Classifier: Programming Language :: Python :: 3.6
